waifuos/__init__.py
waifuos-0.0.0.dist-info/licenses/LICENSE
waifuos-0.0.0.dist-info/METADATA
waifuos-0.0.0.dist-info/WHEEL
waifuos-0.0.0.dist-info/top_level.txt
waifuos-0.0.0.dist-info/RECORD
