Metadata-Version: 2.4
Name: waifuos
Version: 0.0.0
Summary: The software suite for creating your waifu and the world where your waifu lives.💕
Author-email: uezo <uezo@uezo.net>
License: Apache-2.0
Requires-Python: >=3.11
License-File: LICENSE
Dynamic: license-file
